BringApi/BringApi.py
BringApi/__init__.py
BringApi-0.0.5.dist-info/LICENSE
BringApi-0.0.5.dist-info/METADATA
BringApi-0.0.5.dist-info/WHEEL
BringApi-0.0.5.dist-info/top_level.txt
BringApi-0.0.5.dist-info/RECORD
