Metadata-Version: 2.1
Name: BringApi
Version: 0.0.5
Summary: Unofficial Bring! Api
Home-page: https://github.com/philipp2310/bring-api
Author: Philipp Duerr
Author-email: phil@uselessbrickwall.com
License: UNKNOWN
Platform: UNKNOWN
Classifier: Programming Language :: Python :: 3
Classifier: License :: OSI Approved :: GNU General Public License (GPL)
Classifier: Operating System :: OS Independent
Requires-Dist: requests
